setup.py
monerowallet/__init__.py
monerowallet/exceptions/__init__.py
pymonerowallet.egg-info/PKG-INFO
pymonerowallet.egg-info/SOURCES.txt
pymonerowallet.egg-info/dependency_links.txt
pymonerowallet.egg-info/requires.txt
pymonerowallet.egg-info/top_level.txt